pluggy/__init__.py
pluggy/_callers.py
pluggy/_hooks.py
pluggy/_manager.py
pluggy/_result.py
pluggy/_tracing.py
pluggy/_version.py
pluggy-1.1.0.dist-info/LICENSE
pluggy-1.1.0.dist-info/METADATA
pluggy-1.1.0.dist-info/WHEEL
pluggy-1.1.0.dist-info/top_level.txt
pluggy-1.1.0.dist-info/RECORD
